asanak_web_call_client/__init__.py
asanak_web_call_client/client.py
asanak_web_call_client/exceptions.py
asanak_web_call_client-1.0.0.dist-info/licenses/LICENSE
asanak_web_call_client-1.0.0.dist-info/METADATA
asanak_web_call_client-1.0.0.dist-info/WHEEL
asanak_web_call_client-1.0.0.dist-info/top_level.txt
asanak_web_call_client-1.0.0.dist-info/RECORD
