Metadata-Version: 2.4
Name: asanak_web_call_client
Version: 1.0.0
Summary: Asanak Web Call client for making and managing calls via REST API
Author: Farzad Forouzanfar
Author-email: forouzanfar2000f@gmail.com
Classifier: Programming Language :: Python :: 3
Classifier: License :: OSI Approved :: MIT License
Classifier: Operating System :: OS Independent
Requires-Python: >=3.7
License-File: LICENSE
Requires-Dist: requests>=2.25
Dynamic: author
Dynamic: author-email
Dynamic: classifier
Dynamic: description
Dynamic: description-content-type
Dynamic: license-file
Dynamic: requires-dist
Dynamic: requires-python
Dynamic: summary
